adform/Client.py
adform/Credentials.py
odap_adfrom_downloader-1.0.1.dist-info/LICENSE
odap_adfrom_downloader-1.0.1.dist-info/WHEEL
odap_adfrom_downloader-1.0.1.dist-info/METADATA
odap_adfrom_downloader-1.0.1.dist-info/RECORD
